feed_me_not/__init__.py
feed_me_not/gui.py
feed_me_not-0.1.0.dist-info/WHEEL
feed_me_not-0.1.0.dist-info/entry_points.txt
feed_me_not-0.1.0.dist-info/METADATA
feed_me_not-0.1.0.dist-info/RECORD
