Metadata-Version: 2.4
Name: feed-me-not
Version: 0.1.0
Summary: An app to track which foods/ingredients might be causing food digestive issues.
Keywords: food tracking
Author: siru
Author-email: siru <siru@codessh.de>
License-Expression: GPL-3.0-or-later
Classifier: Development Status :: 1 - Planning
Classifier: License :: OSI Approved :: GNU General Public License v3 or later (GPLv3+)
Classifier: Natural Language :: English
Classifier: Programming Language :: Python :: 3
Classifier: Topic :: Office/Business
Classifier: Typing :: Typed
Maintainer: siru
Maintainer-email: siru <siru@codessh.de>
Requires-Python: >=3.13
Project-URL: documentation, https://codeberg.org/siru/feed-me-not/wiki
Project-URL: homepage, https://codessh.de/feed-me-not/
Project-URL: issues, https://codeberg.org/siru/feed-me-not/issues/
Project-URL: source, https://codeberg.org/siru/feed-me-not/
